btreedict.cpython-313-x86_64-linux-musl.so
btreedict-1.0.0.dist-info/WHEEL
btreedict-1.0.0.dist-info/top_level.txt
btreedict-1.0.0.dist-info/METADATA
btreedict-1.0.0.dist-info/RECORD
btreedict-1.0.0.dist-info/licenses/LICENSE
