Metadata-Version: 2.4
Name: btreedict
Version: 1.0.0
Summary: B-Tree data structure implemented in C for Python
Home-page: https://github.com/irazza/btree
Author: Alberto
Author-email: Alberto <alberto.azzari@protonmail.com>
License: MIT
Project-URL: Homepage, https://github.com/irazza/btree
Project-URL: Repository, https://github.com/irazza/btree
Classifier: Development Status :: 4 - Beta
Classifier: Intended Audience :: Developers
Classifier: License :: OSI Approved :: MIT License
Classifier: Programming Language :: C
Classifier: Programming Language :: Python :: 3
Classifier: Programming Language :: Python :: 3.11
Classifier: Programming Language :: Python :: 3.12
Classifier: Programming Language :: Python :: 3.13
Classifier: Topic :: Software Development :: Libraries :: Python Modules
Requires-Python: >=3.11
License-File: LICENSE
Dynamic: author
Dynamic: home-page
Dynamic: license-file
Dynamic: requires-python
